Metadata-Version: 1.1
Name: libcloud-client
Version: 0.0.3
Summary: A lightweight Python client for LibCloud.
Home-page: https://gitlab.com/libcloud/libcloud-client
Author: Yoginth
Author-email: me@yoginth.com
License: Apache License 2.0
Platform: UNKNOWN
Classifier: Programming Language :: Python :: 2
Classifier: Programming Language :: Python :: 2.6
Classifier: Programming Language :: Python :: 2.7
Classifier: Programming Language :: Python :: 3
Classifier: Programming Language :: Python :: 3.3
Classifier: License :: OSI Approved :: Apache Software License
Classifier: Topic :: Software Development :: Testing
